entheogen/__init__.py
entheogen/_generate.py
entheogen/methods.py
entheogen-0.0.1.dist-info/licenses/LICENSE
entheogen-0.0.1.dist-info/METADATA
entheogen-0.0.1.dist-info/WHEEL
entheogen-0.0.1.dist-info/top_level.txt
entheogen-0.0.1.dist-info/RECORD
